udpbus/__init__.py
udpbus-0.4.0.dist-info/METADATA
udpbus-0.4.0.dist-info/WHEEL
udpbus-0.4.0.dist-info/licenses/LICENSE
udpbus-0.4.0.dist-info/RECORD
