Metadata-Version: 2.4
Name: udpbus
Version: 0.4.0
Summary: Simple UDP Message Bus with CBOR Array Protocol
Project-URL: Homepage, https://github.com/blockshake-io/udpbus
Project-URL: Repository, https://github.com/blockshake-io/udpbus
Author: UDPBus Contributors
License: MIT License
License-File: LICENSE
Keywords: bus,cbor,iot,messaging,pubsub,robotics,sensor,udp
Classifier: Development Status :: 4 - Beta
Classifier: Intended Audience :: Developers
Classifier: License :: OSI Approved :: MIT License
Classifier: Programming Language :: Python :: 3
Classifier: Topic :: Software Development :: Libraries :: Python Modules
Classifier: Topic :: System :: Networking
Requires-Python: >=3.8
Requires-Dist: cbor2>=5.0.0
Provides-Extra: dev
Requires-Dist: pytest>=7.0.0; extra == 'dev'
